tarantool/__init__.py
tarantool/connection.py
tarantool/connection_pool.py
tarantool/const.py
tarantool/crud.py
tarantool/dbapi.py
tarantool/error.py
tarantool/mesh_connection.py
tarantool/request.py
tarantool/response.py
tarantool/schema.py
tarantool/space.py
tarantool/types.py
tarantool/utils.py
tarantool/version.py
tarantool/msgpack_ext/__init__.py
tarantool/msgpack_ext/datetime.py
tarantool/msgpack_ext/decimal.py
tarantool/msgpack_ext/error.py
tarantool/msgpack_ext/interval.py
tarantool/msgpack_ext/packer.py
tarantool/msgpack_ext/unpacker.py
tarantool/msgpack_ext/uuid.py
tarantool/msgpack_ext/types/__init__.py
tarantool/msgpack_ext/types/datetime.py
tarantool/msgpack_ext/types/interval.py
tarantool/msgpack_ext/types/timezones/__init__.py
tarantool/msgpack_ext/types/timezones/gen-timezones.sh
tarantool/msgpack_ext/types/timezones/timezones.py
tarantool-1.2.0.dist-info/AUTHORS
tarantool-1.2.0.dist-info/LICENSE
tarantool-1.2.0.dist-info/METADATA
tarantool-1.2.0.dist-info/WHEEL
tarantool-1.2.0.dist-info/top_level.txt
tarantool-1.2.0.dist-info/RECORD
