Metadata-Version: 2.1
Name: tarantool
Version: 1.2.0
Summary: Python client library for Tarantool
Home-page: https://github.com/tarantool/tarantool-python
Author: tarantool-python AUTHORS
Author-email: admin@tarantool.org
License: BSD
Platform: all
Classifier: Intended Audience :: Developers
Classifier: License :: OSI Approved :: BSD License
Classifier: Operating System :: OS Independent
Classifier: Programming Language :: Python :: 3 :: Only
Classifier: Topic :: Database :: Front-Ends
Requires-Python: >=3.6
License-File: LICENSE
License-File: AUTHORS
Requires-Dist: msgpack
Requires-Dist: pytz
Requires-Dist: dataclasses ; python_version <= "3.6"
